
<annotation>
    <folder>images</folder>
    <filename>tomato468.png</filename>
    <size>
        <width>500</width>
        <height>400</height>
        <depth>3</depth>
    </size>
    <segmented>0</segmented>
    <object>
        <name>tomato</name>
        <pose>Unspecified</pose>
        <truncated>0</truncated>
        <occluded>0</occluded>
        <difficult>0</difficult>
        <bndbox>
            <xmin>382</xmin>
            <ymin>11</ymin>
            <xmax>483</xmax>
            <ymax>110</ymax>
        </bndbox>
    </object>
    <object>
        <name>tomato</name>
        <pose>Unspecified</pose>
        <truncated>0</truncated>
        <occluded>0</occluded>
        <difficult>0</difficult>
        <bndbox>
            <xmin>444</xmin>
            <ymin>0</ymin>
            <xmax>479</xmax>
            <ymax>31</ymax>
        </bndbox>
    </object>
</annotation>